sqlalchemy_sessionload-1.1.0.post2.dist-info/METADATA
sqlalchemy_sessionload-1.1.0.post2.dist-info/WHEEL
sqlalchemy_sessionload-1.1.0.post2.dist-info/entry_points.txt
sqlalchemy_sessionload-1.1.0.post2.dist-info/licenses/LICENSE
sqlalchemy_sessionload/__init__.py
sqlalchemy_sessionload/filter.py
sqlalchemy_sessionload/loaders.py
sqlalchemy_sessionload/options.py
sqlalchemy_sessionload/plugin.py
sqlalchemy_sessionload/py.typed
sqlalchemy_sessionload/sort.py
sqlalchemy_sessionload-1.1.0.post2.dist-info/RECORD
