Metadata-Version: 2.1
Name: sqlalchemy-sessionload
Version: 1.1.0.post2
Summary: SQLAlchemy load option that loads only from persisted session instances
Keywords: sqlalchemy,session,loader
Author-Email: Jan Vollmer <jan@vllmr.dev>
License: MIT License
Classifier: Development Status :: 5 - Production/Stable
Classifier: Environment :: Plugins
Classifier: Intended Audience :: Developers
Classifier: License :: OSI Approved :: MIT License
Classifier: Programming Language :: Python :: 3.10
Classifier: Programming Language :: Python :: 3.11
Classifier: Programming Language :: Python :: 3.12
Classifier: Programming Language :: Python :: 3.13
Classifier: Programming Language :: Python :: 3.14
Classifier: Programming Language :: Python :: Implementation :: CPython
Classifier: Typing :: Typed
Project-URL: Source, https://github.com/jvllmr/sqlalchemy-sessionload
Requires-Python: >=3.10
Requires-Dist: sqlalchemy>=2.0.44
